CHANGELOG.md
LICENSE
MANIFEST.in
README.md
setup.cfg
setup.py
oauth2clientziead/__init__.py
oauth2clientziead/_helpers.py
oauth2clientziead/_openssl_crypt.py
oauth2clientziead/_pkce.py
oauth2clientziead/_pure_python_crypt.py
oauth2clientziead/_pycrypto_crypt.py
oauth2clientziead/client.py
oauth2clientziead/clientsecrets.py
oauth2clientziead/crypt.py
oauth2clientziead/file.py
oauth2clientziead/service_account.py
oauth2clientziead/tools.py
oauth2clientziead/transport.py
oauth2clientziead.egg-info/PKG-INFO
oauth2clientziead.egg-info/SOURCES.txt
oauth2clientziead.egg-info/dependency_links.txt
oauth2clientziead.egg-info/requires.txt
oauth2clientziead.egg-info/top_level.txt
oauth2clientziead/contrib/__init__.py
oauth2clientziead/contrib/_appengine_ndb.py
oauth2clientziead/contrib/_metadata.py
oauth2clientziead/contrib/appengine.py
oauth2clientziead/contrib/devshell.py
oauth2clientziead/contrib/dictionary_storage.py
oauth2clientziead/contrib/flask_util.py
oauth2clientziead/contrib/gce.py
oauth2clientziead/contrib/keyring_storage.py
oauth2clientziead/contrib/multiprocess_file_storage.py
oauth2clientziead/contrib/sqlalchemy.py
oauth2clientziead/contrib/xsrfutil.py
oauth2clientziead/contrib/django_util/__init__.py
oauth2clientziead/contrib/django_util/apps.py
oauth2clientziead/contrib/django_util/decorators.py
oauth2clientziead/contrib/django_util/models.py
oauth2clientziead/contrib/django_util/signals.py
oauth2clientziead/contrib/django_util/site.py
oauth2clientziead/contrib/django_util/storage.py
oauth2clientziead/contrib/django_util/views.py
tests/__init__.py
tests/conftest.py
tests/http_mock.py
tests/test__helpers.py
tests/test__pkce.py
tests/test__pure_python_crypt.py
tests/test__pycrypto_crypt.py
tests/test_client.py
tests/test_clientsecrets.py
tests/test_crypt.py
tests/test_file.py
tests/test_jwt.py
tests/test_service_account.py
tests/test_tools.py
tests/test_transport.py
tests/contrib/__init__.py
tests/contrib/test_devshell.py
tests/contrib/test_dictionary_storage.py
tests/contrib/test_flask_util.py
tests/contrib/test_gce.py
tests/contrib/test_keyring_storage.py
tests/contrib/test_metadata.py
tests/contrib/test_multiprocess_file_storage.py
