Metadata-Version: 2.1
Name: oauth2clientziead
Version: 5.0.0
Summary: client library
Home-page: https://github.com/zieadshabkalieh/oauth2clientziead
Author: ZSK
Author-email: zshabkalieh@gmail.com
License: UNKNOWN
Keywords: google oauth 2.0 http client
Platform: UNKNOWN
Classifier: Programming Language :: Python :: 2
Classifier: Programming Language :: Python :: 2.7
Classifier: Programming Language :: Python :: 3
Classifier: Programming Language :: Python :: 3.4
Classifier: Programming Language :: Python :: 3.5
Classifier: Development Status :: 7 - Inactive
Classifier: Intended Audience :: Developers
Classifier: License :: OSI Approved :: Apache Software License
Classifier: Operating System :: POSIX
Classifier: Topic :: Internet :: WWW/HTTP
License-File: LICENSE
